odoo/addons/stock_push_delay/README.rst
odoo/addons/stock_push_delay/__init__.py
odoo/addons/stock_push_delay/__manifest__.py
odoo/addons/stock_push_delay/i18n/it.po
odoo/addons/stock_push_delay/i18n/stock_push_delay.pot
odoo/addons/stock_push_delay/models/__init__.py
odoo/addons/stock_push_delay/models/stock_move.py
odoo/addons/stock_push_delay/models/stock_picking.py
odoo/addons/stock_push_delay/models/stock_rule.py
odoo/addons/stock_push_delay/readme/CONTRIBUTORS.md
odoo/addons/stock_push_delay/readme/DESCRIPTION.md
odoo/addons/stock_push_delay/readme/USAGE.md
odoo/addons/stock_push_delay/static/description/icon.png
odoo/addons/stock_push_delay/static/description/index.html
odoo/addons/stock_push_delay/tests/__init__.py
odoo/addons/stock_push_delay/tests/test_stock_push_delay.py
odoo/addons/stock_push_delay/views/stock_move_views.xml
odoo/addons/stock_push_delay/views/stock_rule_views.xml
odoo_addon_stock_push_delay-17.0.1.1.1.dist-info/METADATA
odoo_addon_stock_push_delay-17.0.1.1.1.dist-info/WHEEL
odoo_addon_stock_push_delay-17.0.1.1.1.dist-info/top_level.txt
odoo_addon_stock_push_delay-17.0.1.1.1.dist-info/RECORD
